emsapi/__init__.py
emsapi/emsapi.py
emsapi/extensions.py
emsapi/version.py
emsapi/models/__init__.py
emsapi/models/adi_ems_web_api_core_dto_data_range.py
emsapi/models/adi_ems_web_api_core_dto_data_range_py3.py
emsapi/models/adi_ems_web_api_core_model_schema_query_result_status.py
emsapi/models/adi_ems_web_api_core_model_schema_query_result_status_py3.py
emsapi/models/adi_ems_web_api_model_error.py
emsapi/models/adi_ems_web_api_model_error_py3.py
emsapi/models/adi_ems_web_api_v2_dto_alert_add_activity.py
emsapi/models/adi_ems_web_api_v2_dto_alert_add_activity_py3.py
emsapi/models/adi_ems_web_api_v2_dto_alert_definition.py
emsapi/models/adi_ems_web_api_v2_dto_alert_definition_py3.py
emsapi/models/adi_ems_web_api_v2_dto_alert_get_activity.py
emsapi/models/adi_ems_web_api_v2_dto_alert_get_activity_py3.py
emsapi/models/adi_ems_web_api_v2_dto_alert_set_definition.py
emsapi/models/adi_ems_web_api_v2_dto_alert_set_definition_py3.py
emsapi/models/adi_ems_web_api_v2_dto_analytic_formula.py
emsapi/models/adi_ems_web_api_v2_dto_analytic_formula_py3.py
emsapi/models/adi_ems_web_api_v2_dto_analytic_group.py
emsapi/models/adi_ems_web_api_v2_dto_analytic_group_contents.py
emsapi/models/adi_ems_web_api_v2_dto_analytic_group_contents_py3.py
emsapi/models/adi_ems_web_api_v2_dto_analytic_group_py3.py
emsapi/models/adi_ems_web_api_v2_dto_analytic_info.py
emsapi/models/adi_ems_web_api_v2_dto_analytic_info_py3.py
emsapi/models/adi_ems_web_api_v2_dto_analytic_set_analytic_collection.py
emsapi/models/adi_ems_web_api_v2_dto_analytic_set_analytic_collection_created.py
emsapi/models/adi_ems_web_api_v2_dto_analytic_set_analytic_collection_created_py3.py
emsapi/models/adi_ems_web_api_v2_dto_analytic_set_analytic_collection_item.py
emsapi/models/adi_ems_web_api_v2_dto_analytic_set_analytic_collection_item_py3.py
emsapi/models/adi_ems_web_api_v2_dto_analytic_set_analytic_collection_py3.py
emsapi/models/adi_ems_web_api_v2_dto_analytic_set_analytic_set.py
emsapi-2.0.0.dist-info/LICENSE
emsapi-2.0.0.dist-info/METADATA
emsapi-2.0.0.dist-info/WHEEL
emsapi-2.0.0.dist-info/top_level.txt
emsapi-2.0.0.dist-info/RECORD
