Metadata-Version: 2.1
Name: emsapi
Version: 2.0.0
Summary: A Python EMS RESTful API Client/Wrapper
Home-page: https://github.com/ge-flight-analytics/emsapi-python
Author: GE Flight Analytics
Author-email: AviationAdiSupport@ge.com
License: MIT
Classifier: Programming Language :: Python :: 3
Classifier: License :: OSI Approved :: MIT License
License-File: LICENSE
Requires-Dist: msrest (>=0.6.10)
Requires-Dist: pandas (>=2.0.3)
